MANIFEST.in
README.md
setup.py
emulator/__init__.py
emulator/common.py
emulator/functions.py
emulator/timer.py
emulator/views.py
emulator.egg-info/PKG-INFO
emulator.egg-info/SOURCES.txt
emulator.egg-info/dependency_links.txt
emulator.egg-info/requires.txt
emulator.egg-info/top_level.txt
emulator/paho/__init__.py
emulator/paho/mqtt/__init__.py
emulator/paho/mqtt/client.py
emulator/paho/mqtt/matcher.py
emulator/paho/mqtt/publish.py
emulator/paho/mqtt/subscribe.py
emulator/static/script.js
emulator/static/style.css
emulator/static/images/alarm.png
emulator/static/images/climax.png
emulator/static/images/dimmer.png
emulator/static/images/flood.png
emulator/static/images/light.png
emulator/static/images/lock.png
emulator/static/images/motion.png
emulator/static/images/multi.png
emulator/static/images/plug.png
emulator/static/images/plus.png
emulator/static/images/strip.png
emulator/static/images/switch.png
emulator/static/images/thermostat.png
emulator/static/prop_files/alarm.json
emulator/static/prop_files/climax.json
emulator/static/prop_files/dimmer.json
emulator/static/prop_files/flood.json
emulator/static/prop_files/light.json
emulator/static/prop_files/lock.json
emulator/static/prop_files/multi.json
emulator/static/prop_files/plus.json
emulator/static/prop_files/strip.json
emulator/static/prop_files/switch.json
emulator/templates/front.html