Metadata-Version: 1.0
Name: emulator
Version: 1.8.6
Summary: Python-Flask application to emulate IoT devices
Home-page: https://github.com/futurehomeno/emulator
Author: FutureHome
Author-email: fh@futurehome.no
License: UNKNOWN
Platform: UNKNOWN
